dbest/__init__.py
dbest/cli.py
dbest/data_loader.py
dbest/dbestclient.py
dbest/eval.py
dbest/evaluate2d.py
dbest/evaluation.py
dbest/generate_random.py
dbest/logs.py
dbest/notebookSchedule.py
dbest/plot_results.py
dbest/qreg.py
dbest/query_engine.py
dbest/tools.py
dbest-2.1.dist-info/LICENSE
dbest-2.1.dist-info/METADATA
dbest-2.1.dist-info/WHEEL
dbest-2.1.dist-info/top_level.txt
dbest-2.1.dist-info/RECORD
