Metadata-Version: 2.1
Name: dbest
Version: 2.1
Summary: Model-based Approximate Query Processing (AQP) engine.
Home-page: https://github.com/qingzma/DBEst
Author: Qingzhi Ma
Author-email: Q.Ma.2@warwick.ac.uk
License: Copyright (c) 2018, Qingzhi Ma
Requires-Dist: xgboost
Requires-Dist: numpy
